root_io/__init__.py
root_io/sdk/__init__.py
root_io/sdk/cloud_client/__init__.py
root_io/sdk/cloud_client/api_client.py
root_io/sdk/cloud_client/api_response.py
root_io/sdk/cloud_client/configuration.py
root_io/sdk/cloud_client/exceptions.py
root_io/sdk/cloud_client/rest.py
root_io/sdk/cloud_client/api/__init__.py
root_io/sdk/cloud_client/api/account_api.py
root_io/sdk/cloud_client/api/api_keys_api.py
root_io/sdk/cloud_client/api/inventory_api.py
root_io/sdk/cloud_client/api/invite_api.py
root_io/sdk/cloud_client/api/organization_api.py
root_io/sdk/cloud_client/api/organization_membership_api.py
root_io/sdk/cloud_client/api/security_findings_api.py
root_io/sdk/cloud_client/api/statistics_api.py
root_io/sdk/cloud_client/api/v_scan_reports_api.py
root_io/sdk/cloud_client/api/workspace_membership_api.py
root_io/sdk/cloud_client/api/workspace_security_findings_api.py
root_io/sdk/cloud_client/api/workspaces_api.py
root_io/sdk/cloud_client/models/__init__.py
root_io/sdk/cloud_client/models/account.py
root_io/sdk/cloud_client/models/add_workspace_tags_request.py
root_io/sdk/cloud_client/models/api_key.py
root_io/sdk/cloud_client/models/bulk_add_members_request.py
root_io/sdk/cloud_client/models/create_api_key_request.py
root_io/sdk/cloud_client/models/create_org_invite_request.py
root_io/sdk/cloud_client/models/create_org_invite_response.py
root_io/sdk/cloud_client/models/create_organization_request.py
root_io/sdk/cloud_client/models/create_workspace_request.py
root_io/sdk/cloud_client/models/create_ws_invite_response.py
root_io/sdk/cloud_client/models/entities_finding_status.py
root_io/sdk/cloud_client/models/entities_org_role.py
root_io/sdk/cloud_client/models/entities_resolution.py
root_io/sdk/cloud_client/models/entities_scanner_name.py
root_io/sdk/cloud_client/models/entities_security_finding_comment_kind.py
root_io/sdk/cloud_client/models/entities_security_finding_severity.py
root_io/sdk/cloud_client/models/entities_vscan_report_upload_status.py
rootio_client-1.1.1.dist-info/LICENSE
rootio_client-1.1.1.dist-info/METADATA
rootio_client-1.1.1.dist-info/WHEEL
rootio_client-1.1.1.dist-info/top_level.txt
rootio_client-1.1.1.dist-info/RECORD
